[{"place_id": 309085709, "licence": "Data \u00a9 OpenStreetMap contributors, ODbL 1.0. http://osm.org/copyright", "osm_type": "node", "osm_id": 6114280545, "lat": "34.5908349", "lon": "-118.1196007", "class": "railway", "type": "station", "place_rank": 30, "importance": 0.2780150946188139, "addresstype": "railway", "name": "Palmdale", "display_name": "Palmdale, 1, Palmdale, California, 93550, United States", "boundingbox": ["34.5858349", "34.5958349", "-118.1246007", "-118.1146007"], "geojson": {"type": "Point", "coordinates": [-118.1196007, 34.5908349]}}, {"place_id": 309114094, "licence": "Data \u00a9 OpenStreetMap contributors, ODbL 1.0. http://osm.org/copyright", "osm_type": "node", "osm_id": 6150649386, "lat": "34.5914606", "lon": "-118.1193761", "class": "railway", "type": "stop", "place_rank": 30, "importance": 9.99999999995449e-06, "addresstype": "railway", "name": "Palmdale", "display_name": "Palmdale, 1, Palmdale, California, 93550, United States", "boundingbox": ["34.5914106", "34.5915106", "-118.1194261", "-118.1193261"], "geojson": {"type": "Point", "coordinates": [-118.1193761, 34.5914606]}}, {"place_id": 309110382, "licence": "Data \u00a9 OpenStreetMap contributors, ODbL 1.0. http://osm.org/copyright", "osm_type": "node", "osm_id": 6150649387, "lat": "34.5900669", "lon": "-118.1191553", "class": "railway", "type": "stop", "place_rank": 30, "importance": 9.99999999995449e-06, "addresstype": "railway", "name": "Palmdale", "display_name": "Palmdale, 1, Palmdale, California, 93550, United States", "boundingbox": ["34.5900169", "34.5901169", "-118.1192053", "-118.1191053"], "geojson": {"type": "Point", "coordinates": [-118.1191553, 34.5900669]}}, {"place_id": 309090395, "licence": "Data \u00a9 OpenStreetMap contributors, ODbL 1.0. http://osm.org/copyright", "osm_type": "way", "osm_id": 135245202, "lat": "34.6274752", "lon": "-118.09397562209404", "class": "aeroway", "type": "aerodrome", "place_rank": 30, "importance": 0.2844409508461066, "addresstype": "aeroway", "name": "USAF Plant 42 / Palmdale Regional Airport", "display_name": "USAF Plant 42 / Palmdale Regional Airport, East Avenue O 8, Palmdale, California, United States", "boundingbox": ["34.6080273", "34.6454353", "-118.1268240", "-118.0507138"], "geojson": {"type": "Polygon", "coordinates": [[[-118.126824, 34.6442159], [-118.125631, 34.6350871], [-118.1226153, 34.6206676], [-118.1113774, 34.6205135], [-118.1066919, 34.6205528], [-118.1031075, 34.620575], [-118.1030526, 34.6205754], [-118.1030183, 34.6205756], [-118.1029768, 34.6203872], [-118.1029798, 34.6200524], [-118.1028817, 34.6174972], [-118.1028828, 34.6167189], [-118.1026786, 34.6117472], [-118.0947215, 34.6126916], [-118.0947186, 34.6080273], [-118.0707589, 34.6095689], [-118.0707691, 34.6231596], [-118.0702673, 34.6234734], [-118.0676172, 34.6251867], [-118.0602072, 34.6297637], [-118.0507138, 34.6359089], [-118.0599486, 34.6454353], [-118.126824, 34.6442159]]]}}, {"place_id": 309090332, "licence": "Data \u00a9 OpenStreetMap contributors, ODbL 1.0. http://osm.org/copyright", "osm_type": "way", "osm_id": 135245202, "lat": "34.6274752", "lon": "-118.09397562209404", "class": "military", "type": "airfield", "place_rank": 30, "importance": 0.2844409508461066, "addresstype": "military", "name": "USAF Plant 42 / Palmdale Regional Airport", "display_name": "USAF Plant 42 / Palmdale Regional Airport, East Avenue O 8, Palmdale, California, United States", "boundingbox": ["34.6080273", "34.6454353", "-118.1268240", "-118.0507138"], "geojson": {"type": "Polygon", "coordinates": [[[-118.126824, 34.6442159], [-118.125631, 34.6350871], [-118.1226153, 34.6206676], [-118.1113774, 34.6205135], [-118.1066919, 34.6205528], [-118.1031075, 34.620575], [-118.1030526, 34.6205754], [-118.1030183, 34.6205756], [-118.1029768, 34.6203872], [-118.1029798, 34.6200524], [-118.1028817, 34.6174972], [-118.1028828, 34.6167189], [-118.1026786, 34.6117472], [-118.0947215, 34.6126916], [-118.0947186, 34.6080273], [-118.0707589, 34.6095689], [-118.0707691, 34.6231596], [-118.0702673, 34.6234734], [-118.0676172, 34.6251867], [-118.0602072, 34.6297637], [-118.0507138, 34.6359089], [-118.0599486, 34.6454353], [-118.126824, 34.6442159]]]}}]